Metadata-Version: 1.0
Name: timor
Version: 0.0.1
Summary: Just a test
Home-page: https://github.com/puke3615
Author: puke
Author-email: 1129090915@qq.com
License: UNKNOWN
Platform: UNKNOWN
